shtu_venus-0.11.dist-info/DESCRIPTION.rst
shtu_venus-0.11.dist-info/METADATA
shtu_venus-0.11.dist-info/RECORD
shtu_venus-0.11.dist-info/WHEEL
shtu_venus-0.11.dist-info/metadata.json
shtu_venus-0.11.dist-info/top_level.txt
src/__init__.py
src/main.py
src/base/__init__.py
src/base/base.py
src/config/__init__.py
src/config/config.py
src/config/config_manager.py
src/config/utils.py
src/config/netcfgs/__init__.py
src/config/netcfgs/basic_modules_spec.py
src/config/netcfgs/net_spec_edict.py
src/config/paracfgs/__init__.py
src/config/paracfgs/class_example.py
src/config/paracfgs/edict_example.py
src/dataset/__init__.py
src/dataset/batchdataset.py
src/dataset/concatdataset.py
src/dataset/dataset.py
src/dataset/listdataset.py
src/dataset/resampledataset.py
src/dataset/shuffledataset.py
src/dataset/splitdataset.py
src/dataset/tensordataset.py
src/dataset/transformdataset.py
src/engine/__init__.py
src/engine/engine.py
src/logger/__init__.py
src/logger/logger.py
src/logger/visdomlogger.py
src/meter/__init__.py
src/meter/apmeter.py
src/meter/aucmeter.py
src/meter/averagevaluemeter.py
src/meter/classerrormeter.py
src/meter/confusionmeter.py
src/meter/mapmeter.py
src/meter/meter.py
src/meter/movingaveragevaluemeter.py
src/meter/msemeter.py
src/meter/timemeter.py
src/opt/__init__.py
src/opt/hyper_optimizer.py
src/test/__init__.py
src/test/test_config.py
src/test/test_visual.py
src/utils/__init__.py
src/utils/table.py
src/visual/__init__.py
src/visual/visual.py
