Metadata-Version: 2.0
Name: shtu-venus
Version: 0.11
Summary: A deep learning experiment tool to help you develop and manage your project
Home-page: https://github.com/ShanghaiTechVENUS/venus/tree/master
Author: Shipeng Yan
Author-email: yanshp@shanghaitech.edu.cn
License: MIT
Platform: UNKNOWN
Classifier: License :: OSI Approved :: MIT License
Classifier: Programming Language :: Python
Classifier: Programming Language :: Python :: 3
Classifier: Programming Language :: Python :: 3.6
Classifier: Programming Language :: Python :: Implementation :: CPython
Classifier: Programming Language :: Python :: Implementation :: PyPy
Requires-Python: >=2.7.0
Requires-Dist: easydict
